README.md
setup.cfg
setup.py
test/test_account.py
test/test_account_service_api.py
test/test_account_service_auth_type.py
test/test_account_service_auto_tagging_enabled.py
test/test_account_service_budget.py
test/test_account_service_delivery_status.py
test/test_account_service_get_response.py
test/test_account_service_include_test_account.py
test/test_account_service_is_test_account.py
test/test_account_service_limit_charge_type.py
test/test_account_service_mutate_response.py
test/test_account_service_operation.py
test/test_account_service_page.py
test/test_account_service_return_value.py
test/test_account_service_selector.py
test/test_account_service_status.py
test/test_account_service_type.py
test/test_account_service_value.py
test/test_account_shared.py
test/test_account_shared_service_api.py
test/test_account_shared_service_get_response.py
test/test_account_shared_service_mutate_response.py
test/test_account_shared_service_operation.py
test/test_account_shared_service_page.py
test/test_account_shared_service_return_value.py
test/test_account_shared_service_selector.py
test/test_account_shared_service_value.py
test/test_account_tracking_url.py
test/test_account_tracking_url_service_api.py
test/test_account_tracking_url_service_get_response.py
test/test_account_tracking_url_service_mutate_response.py
test/test_account_tracking_url_service_operation.py
test/test_account_tracking_url_service_page.py
test/test_account_tracking_url_service_return_value.py
test/test_account_tracking_url_service_selector.py
test/test_account_tracking_url_service_url_approval_status.py
test/test_account_tracking_url_service_value.py
test/test_ad_group.py
test/test_ad_group_ad.py
test/test_ad_group_ad_label.py
test/test_ad_group_ad_label_service_api.py
test/test_ad_group_ad_label_service_mutate_response.py
test/test_ad_group_ad_label_service_operation.py
test/test_ad_group_ad_label_service_return_value.py
test/test_ad_group_ad_label_service_value.py
test/test_ad_group_ad_service_ad.py
yahoo_ads_search.egg-info/PKG-INFO
yahoo_ads_search.egg-info/SOURCES.txt
yahoo_ads_search.egg-info/dependency_links.txt
yahoo_ads_search.egg-info/requires.txt
yahoo_ads_search.egg-info/top_level.txt
