Metadata-Version: 1.0
Name: yahoo-ads-search
Version: 1.0.0
Summary: Yahoo!広告 検索広告 API リファレンス / Yahoo! Ads Search Ads API Reference
Home-page: UNKNOWN
Author: OpenAPI Generator community
Author-email: team@openapitools.org
License: UNKNOWN
Keywords: OpenAPI,OpenAPI-Generator,Yahoo!広告 検索広告 API リファレンス / Yahoo! Ads Search Ads API Reference
Platform: UNKNOWN
